invenio_records_ui/__init__.py
invenio_records_ui/config.py
invenio_records_ui/ext.py
invenio_records_ui/signals.py
invenio_records_ui/utils.py
invenio_records_ui/views.py
invenio_records_ui/templates/invenio_records_ui/base.html
invenio_records_ui/templates/invenio_records_ui/detail.html
invenio_records_ui/templates/invenio_records_ui/export.html
invenio_records_ui/templates/invenio_records_ui/export_well.html
invenio_records_ui/templates/invenio_records_ui/tombstone.html
invenio_records_ui/templates/semantic-ui/invenio_records_ui/base.html
invenio_records_ui/templates/semantic-ui/invenio_records_ui/detail.html
invenio_records_ui/templates/semantic-ui/invenio_records_ui/export.html
invenio_records_ui/templates/semantic-ui/invenio_records_ui/export_well.html
invenio_records_ui/templates/semantic-ui/invenio_records_ui/tombstone.html
invenio_records_ui/translations/messages.pot
invenio_records_ui/translations/ar/LC_MESSAGES/messages.mo
invenio_records_ui/translations/ar/LC_MESSAGES/messages.po
invenio_records_ui/translations/bg/LC_MESSAGES/messages.mo
invenio_records_ui/translations/bg/LC_MESSAGES/messages.po
invenio_records_ui/translations/ca/LC_MESSAGES/messages.mo
invenio_records_ui/translations/ca/LC_MESSAGES/messages.po
invenio_records_ui/translations/cs/LC_MESSAGES/messages.mo
invenio_records_ui/translations/cs/LC_MESSAGES/messages.po
invenio_records_ui/translations/da/LC_MESSAGES/messages.mo
invenio_records_ui/translations/da/LC_MESSAGES/messages.po
invenio_records_ui/translations/de/LC_MESSAGES/messages.mo
invenio_records_ui/translations/de/LC_MESSAGES/messages.po
invenio_records_ui/translations/el/LC_MESSAGES/messages.mo
invenio_records_ui/translations/el/LC_MESSAGES/messages.po
invenio_records_ui/translations/es/LC_MESSAGES/messages.mo
invenio_records_ui/translations/es/LC_MESSAGES/messages.po
invenio_records_ui/translations/et/LC_MESSAGES/messages.mo
invenio_records_ui/translations/et/LC_MESSAGES/messages.po
invenio_records_ui-2.1.2.dist-info/licenses/AUTHORS.rst
invenio_records_ui-2.1.2.dist-info/licenses/LICENSE
invenio_records_ui-2.1.2.dist-info/METADATA
invenio_records_ui-2.1.2.dist-info/WHEEL
invenio_records_ui-2.1.2.dist-info/entry_points.txt
invenio_records_ui-2.1.2.dist-info/top_level.txt
invenio_records_ui-2.1.2.dist-info/RECORD
