Metadata-Version: 2.4
Name: invenio-records-ui
Version: 2.1.2
Summary: "User interface for Invenio-Records."
Home-page: https://github.com/inveniosoftware/invenio-records-ui
Author: CERN
Author-email: info@inveniosoftware.org
License: MIT
Keywords: invenio records ui
Platform: any
Classifier: Development Status :: 5 - Production/Stable
Requires-Python: >=3.7
License-File: LICENSE
License-File: AUTHORS.rst
Requires-Dist: invenio-base<3.0.0,>=2.0.0
Requires-Dist: invenio-i18n<4.0.0,>=3.0.0
Requires-Dist: invenio-pidstore<3.0.0,>=2.0.0
Requires-Dist: invenio-records<4.0.0,>=3.0.0
Provides-Extra: tests
Requires-Dist: pytest-black-ng>=0.4.0; extra == "tests"
Requires-Dist: invenio-access<5.0.0,>=4.0.0; extra == "tests"
Requires-Dist: invenio-accounts<7.0.0,>=6.0.0; extra == "tests"
Requires-Dist: invenio-db[mysql,postgresql,versioning]<3.0.0,>=2.0.0; extra == "tests"
Requires-Dist: pytest-invenio<4.0.0,>=3.0.0; extra == "tests"
Requires-Dist: sphinx>=4.5; extra == "tests"
Provides-Extra: docs
Dynamic: license-file
